modules/__init__.py
modules/database.py
modules/electricitymaps_api.py
modules/energy_usage.py
modules/file_storage.py
modules/grafana_display.py
modules/kasa_monitor.py
modules/watttime_api.py
kasa_carbon-0.1.dist-info/LICENSE
kasa_carbon-0.1.dist-info/METADATA
kasa_carbon-0.1.dist-info/WHEEL
kasa_carbon-0.1.dist-info/entry_points.txt
kasa_carbon-0.1.dist-info/top_level.txt
kasa_carbon-0.1.dist-info/RECORD
