Metadata-Version: 2.1
Name: kasa-carbon
Version: 0.1
License-File: LICENSE
Requires-Dist: python-kasa ==0.5.4
Requires-Dist: pytest ==7.4.0
Requires-Dist: pytest-asyncio ==0.21.1
Requires-Dist: psycopg2-binary ==2.9.9
Requires-Dist: asyncpg ==0.29.0
Requires-Dist: pytz ==2023.3.post1
Requires-Dist: aiohttp ==3.9.1
